expviz/__init__.py
expviz/expviz.py
expviz/version.py
expviz-0.0.4.dist-info/METADATA
expviz-0.0.4.dist-info/WHEEL
expviz-0.0.4.dist-info/top_level.txt
expviz-0.0.4.dist-info/RECORD
