Metadata-Version: 2.1
Name: expviz
Version: 0.0.4
Summary: Visualize experiments tables and figures.
Home-page: https://github.com/fuzihaofzh/expviz
Author: 
Author-email: 
Keywords: Shell env
Classifier: Programming Language :: Python :: 3.7
Requires-Dist: matplotlib
